st_dragdrop_list/__init__.py
st_dragdrop_list/frontend/build/asset-manifest.json
st_dragdrop_list/frontend/build/bootstrap.min.css
st_dragdrop_list/frontend/build/index.html
st_dragdrop_list/frontend/build/static/js/2.131be12c.chunk.js
st_dragdrop_list/frontend/build/static/js/2.131be12c.chunk.js.LICENSE.txt
st_dragdrop_list/frontend/build/static/js/2.131be12c.chunk.js.map
st_dragdrop_list/frontend/build/static/js/main.2301dc13.chunk.js
st_dragdrop_list/frontend/build/static/js/main.2301dc13.chunk.js.map
st_dragdrop_list/frontend/build/static/js/runtime-main.69020042.js
st_dragdrop_list/frontend/build/static/js/runtime-main.69020042.js.map
Streamlit_DragDropList-0.0.1.dist-info/LICENSE
Streamlit_DragDropList-0.0.1.dist-info/METADATA
Streamlit_DragDropList-0.0.1.dist-info/WHEEL
Streamlit_DragDropList-0.0.1.dist-info/top_level.txt
Streamlit_DragDropList-0.0.1.dist-info/RECORD
