Metadata-Version: 2.1
Name: Streamlit-DragDropList
Version: 0.0.1
Summary: Streamlit component of draggable list
Home-page: 
Author: Marc B
Author-email: none@gmail.com
Requires-Python: >=3.6
License-File: LICENSE
Requires-Dist: streamlit (>=0.63)
